setup.py
sol/__init__.py
sol/config.py
sol/magi.py
sol/mt_gui.py
sol/setup_gui.py
sol/test_gui.py
sol/themer.py
sol/database/__init__.py
sol/database/clip.py
sol/database/database.py
sol/database/thumbs.py
sol/gui/__init__.py
sol/gui/lib_org/__init__.py
sol/gui/lib_org/lib_org.py
sol/gui/lib_org/sub_wins.py
sol/gui/tk_gui/__init__.py
sol/gui/tk_gui/clip_collections.py
sol/gui/tk_gui/clip_control.py
sol/gui/tk_gui/midi_config.py
sol/gui/tk_gui/sample_clip.png
sol/gui/tk_gui/sample_thumb.png
sol/gui/tk_gui/tkdnd.py
sol/inputs/__init__.py
sol/inputs/midi.py
sol/inputs/osc.py
sol/inputs/test_osc_server.py
sol/models/__init__.py
sol/models/isadorabl/__init__.py
sol/models/isadorabl/loader.py
sol/models/isadorabl/model.py
sol/models/memepv/__init__.py
sol/models/memepv/model.py
sol/models/resolume/__init__.py
sol/models/resolume/load_avc.py
sol/models/resolume/model.py
sol/themes/__init__.py
sol/themes/dark_like_my_soul.py
sol/themes/hotline_miami.py
sol/themes/light_gray.py
sol_vj.egg-info/PKG-INFO
sol_vj.egg-info/SOURCES.txt
sol_vj.egg-info/dependency_links.txt
sol_vj.egg-info/entry_points.txt
sol_vj.egg-info/requires.txt
sol_vj.egg-info/top_level.txt