Metadata-Version: 1.1
Name: sol-vj
Version: 2.1.5
Summary: sol - fixes for resolume
Home-page: https://github.com/pussinboot/sol
Author: pussinboots
Author-email: mkaynospam@gmail.com
License: MIT
Keywords: vj,resolume,video
Platform: UNKNOWN
Classifier: Development Status :: 4 - Beta
Classifier: Intended Audience :: Developers
Classifier: Topic :: Utilities
Classifier: License :: OSI Approved :: MIT License
Classifier: Programming Language :: Python :: 3
